django_rate_limiter/__init__.py
django_rate_limiter/algorithms.py
django_rate_limiter/apps.py
django_rate_limiter/backends.py
django_rate_limiter/decorators.py
django_rate_limiter/exceptions.py
django_rate_limiter/middleware.py
django_rate_limiter/models.py
django_rate_limiter/utils.py
django_rate_limiter/management/__init__.py
django_rate_limiter/management/commands/__init__.py
django_rate_limiter/management/commands/cleanup_rate_limits.py
django_rate_limiter/migrations/0001_initial.py
django_rate_limiter/migrations/__init__.py
django_rate_limiter_goosebumps-1.0.2.dist-info/licenses/LICENSE
django_rate_limiter_goosebumps-1.0.2.dist-info/METADATA
django_rate_limiter_goosebumps-1.0.2.dist-info/WHEEL
django_rate_limiter_goosebumps-1.0.2.dist-info/top_level.txt
django_rate_limiter_goosebumps-1.0.2.dist-info/RECORD
